pycliarr/__init__.py
pycliarr/version.py
pycliarr/api/__init__.py
pycliarr/api/base_api.py
pycliarr/api/base_media.py
pycliarr/api/exceptions.py
pycliarr/api/radarr.py
pycliarr/api/sonarr.py
pycliarr/cli/__init__.py
pycliarr/cli/cli.py
pycliarr/cli/cli_cmd.py
pycliarr/cli/utils.py
pycliarr-1.0.27.dist-info/LICENSE
pycliarr-1.0.27.dist-info/METADATA
pycliarr-1.0.27.dist-info/WHEEL
pycliarr-1.0.27.dist-info/entry_points.txt
pycliarr-1.0.27.dist-info/top_level.txt
pycliarr-1.0.27.dist-info/RECORD
