Metadata-Version: 2.1
Name: pycliarr
Version: 1.0.27
Summary: Python client for radarr and sonarr
Home-page: https://github.com/vche/pycliarr
Author: Vivien Chene
Author-email: viv@vivc.org
Keywords: python tool
Classifier: Programming Language :: Python :: 3.6
Classifier: Programming Language :: Python :: 3.7
Classifier: Programming Language :: Python :: 3.8
Classifier: Programming Language :: Python :: 3.9
Classifier: Programming Language :: Python :: 3.10
Classifier: Programming Language :: Python :: 3.11
Classifier: Programming Language :: Python :: 3.12
Classifier: Development Status :: 5 - Production/Stable
Classifier: Topic :: Home Automation
Requires-Python: >=3.6
License-File: LICENSE
Requires-Dist: requests
Requires-Dist: m2r2
